{
	"name": "AzureSqlTable18",
	"properties": {
		"linkedServiceName": {
			"referenceName": "AzureSqlDatabase_PCRM",
			"type": "LinkedServiceReference"
		},
		"annotations": [],
		"type": "AzureSqlTable",
		"schema": [
			{
				"name": "file_name",
				"type": "nvarchar"
			},
			{
				"name": "success",
				"type": "nvarchar"
			},
			{
				"name": "date",
				"type": "date"
			},
			{
				"name": "system",
				"type": "nvarchar"
			},
			{
				"name": "record_detail",
				"type": "nvarchar"
			}
		]
	}
}